[{"x": 37.8680781, "y": -122.2579783, "weight": 4.0, "name": "Pancho's", "cluster": 0}, {"x": 37.8705337, "y": -122.2663047, "weight": 4.0, "name": "La Cascada Taqueria", "cluster": 1}, {"x": 37.8690986, "y": -122.2596091, "weight": 4.4668916761331685, "name": "Taqueria Reyes", "cluster": 0}, {"x": 37.866061, "y": -122.2580606, "weight": 4.469319643634, "name": "Remy's Mexican Restaurant", "cluster": 0}, {"x": 37.8755679, "y": -122.2602616, "weight": 4.404667950879303, "name": "La Burrita 2", "cluster": 2}, {"x": 37.8755809, "y": -122.259984, "weight": 4.51855882455086, "name": "Celia's", "cluster": 2}, {"x": 37.8686684, "y": -122.259748, "weight": 4.543777313659495, "name": "Taqueria El Tacontento", "cluster": 0}, {"x": 37.8679766, "y": -122.2575506, "weight": 4.487049927316542, "name": "La Burrita", "cluster": 0}, {"x": 37.869201, "y": -122.256421, "weight": 4.700262199448374, "name": "Taco Truck", "cluster": 0}, {"x": 37.86684, "y": -122.2588129, "weight": 4.555605873278931, "name": "Gordo Taqueria", "cluster": 0}, {"x": 37.8680114, "y": -122.2583343, "weight": 4.472393584139639, "name": "Cafe Durant", "cluster": 0}, {"x": 37.8683664, "y": -122.2590498, "weight": 4.3935008403125835, "name": "Chipotle Mexican Grill", "cluster": 0}, {"x": 37.865831, "y": -122.25802, "weight": 4.69754858871215, "name": "La Fiesta Mexican Restaurant", "cluster": 0}]